missingValues_python/missingValues.py
missingValues_kjindal_101703299-1.0.2.dist-info/LICENSE.txt
missingValues_kjindal_101703299-1.0.2.dist-info/METADATA
missingValues_kjindal_101703299-1.0.2.dist-info/WHEEL
missingValues_kjindal_101703299-1.0.2.dist-info/entry_points.txt
missingValues_kjindal_101703299-1.0.2.dist-info/top_level.txt
missingValues_kjindal_101703299-1.0.2.dist-info/RECORD
