Metadata-Version: 2.1
Name: missingValues-kjindal-101703299
Version: 1.0.2
Summary: A python package to handle Missing Values using SimpleImputer Class
Home-page: UNKNOWN
Author: Kunal Jindal
Author-email: kjindal_be17@thapar.edu
License: UNKNOWN
Platform: UNKNOWN
Classifier: Programming Language :: Python :: 3
Classifier: License :: OSI Approved :: MIT License
Classifier: Operating System :: OS Independent
Requires-Python: >=3.6
Requires-Dist: requests
